README.md
setup.cfg
setup.py
spectramanipulator/__init__.py
spectramanipulator/__main__.py
spectramanipulator/console.py
spectramanipulator/dataloader.py
spectramanipulator/exporter.py
spectramanipulator/general_model.py
spectramanipulator/gl_plotter.py
spectramanipulator/logger.py
spectramanipulator/menubar.py
spectramanipulator/misc.py
spectramanipulator/plotwidget.py
spectramanipulator/project.py
spectramanipulator/qt_task.py
spectramanipulator/script_old.py
spectramanipulator/settings.py
spectramanipulator/singleton.py
spectramanipulator/spectrum.py
spectramanipulator/spectrum_old.py
spectramanipulator/treewidget.py
spectramanipulator/update.py
spectramanipulator/user_namespace.py
spectramanipulator/windows.py
spectramanipulator.egg-info/PKG-INFO
spectramanipulator.egg-info/SOURCES.txt
spectramanipulator.egg-info/dependency_links.txt
spectramanipulator.egg-info/requires.txt
spectramanipulator.egg-info/top_level.txt
spectramanipulator/dialogs/__init__.py
spectramanipulator/dialogs/checkbox_rc.py
spectramanipulator/dialogs/combobox_cb.py
spectramanipulator/dialogs/dial_lineedit.py
spectramanipulator/dialogs/export_spectra_as.py
spectramanipulator/dialogs/fitdialog.py
spectramanipulator/dialogs/fitresult.py
spectramanipulator/dialogs/fitwidget.py
spectramanipulator/dialogs/fitwidget_old.py
spectramanipulator/dialogs/genericinputdialog.py
spectramanipulator/dialogs/genericinputwidget.py
spectramanipulator/dialogs/gui_export_spectra_as.py
spectramanipulator/dialogs/gui_fit.py
spectramanipulator/dialogs/gui_fit_widget.py
spectramanipulator/dialogs/gui_fit_widget_old.py
spectramanipulator/dialogs/gui_interpolate_dialog.py
spectramanipulator/dialogs/gui_intintinputdialog.py
spectramanipulator/dialogs/gui_load_kinetics.py
spectramanipulator/dialogs/gui_rename_dialog.py
spectramanipulator/dialogs/gui_settings.py
spectramanipulator/dialogs/int_int_inputdialog.py
spectramanipulator/dialogs/interpolate_dialog.py
spectramanipulator/dialogs/load_kinetics_dialog.py
spectramanipulator/dialogs/mylineedit.py
spectramanipulator/dialogs/param_settings_dialog.py
spectramanipulator/dialogs/rangewidget.py
spectramanipulator/dialogs/rename_dialog.py
