Metadata-Version: 1.2
Name: spectramanipulator
Version: 0.1.6
Summary: Spectra Manipulator based on pyqtgraph
Home-page: https://github.com/dmadea/Spectra-Manipulator
Author: Dominik Madea
Author-email: dominik.madea@gmail.com
License: UNKNOWN
Download-URL: https://github.com/dmadea/Spectra-Manipulator/archive/refs/tags/v0.1.6.tar.gz
Keywords: python,spectra manipulator
Platform: UNKNOWN
Classifier: Development Status :: 3 - Alpha
Classifier: Intended Audience :: Education
Classifier: Programming Language :: Python :: 3
Classifier: Operating System :: MacOS :: MacOS X
Classifier: Operating System :: Microsoft :: Windows
Classifier: Intended Audience :: End Users/Desktop
Classifier: Intended Audience :: Science/Research
Classifier: License :: OSI Approved :: MIT License
Classifier: Natural Language :: English
Requires-Python: >3.7.1
